{
  "title": "11-year-olds who report eating sweets (including chocolate) daily",
  "unit": "percentage",
  "data": [
    { "country": "Armenia", "girls": 47, "boys": 42 },
    { "country": "Tajikistan", "girls": 47, "boys": 37 },
    { "country": "Bulgaria", "girls": 41, "boys": 38 },
    { "country": "Austria", "girls": 42, "boys": 35 },
    { "country": "Romania", "girls": 42, "boys": 32 },
    { "country": "Malta", "girls": 43, "boys": 31 },
    { "country": "Germany", "girls": 42, "boys": 30 },
    { "country": "United Kingdom (Scotland)", "girls": 37, "boys": 32 },
    { "country": "Slovakia", "girls": 38, "boys": 30 },
    { "country": "Serbia", "girls": 38, "boys": 30 },
    { "country": "Luxembourg", "girls": 38, "boys": 30 },
    { "country": "Netherlands (Kingdom of the)", "girls": 36, "boys": 32 },
    { "country": "Hungary", "girls": 33, "boys": 29 },
    { "country": "Macedonia", "girls": 34, "boys": 28 },
    { "country": "Switzerland", "girls": 35, "boys": 28 },
    { "country": "Denmark (Greenland)", "girls": 33, "boys": 24 },
    { "country": "Estonia", "girls": 31, "boys": 25 },
    { "country": "Italy", "girls": 30, "boys": 26 },
    { "country": "Republic of Moldova", "girls": 30, "boys": 25 },
    { "country": "Albania", "girls": 30, "boys": 24 },
    { "country": "Belgium (Flemish)", "girls": 29, "boys": 23 },
    { "country": "Poland", "girls": 29, "boys": 22 },
    { "country": "Cyprus", "girls": 29, "boys": 20 },
    { "country": "Croatia", "girls": 29, "boys": 22 },
    { "country": "United Kingdom (England)", "girls": 26, "boys": 23 },
    { "country": "United Kingdom (Wales)", "girls": 25, "boys": 23 },
    { "country": "Kazakhstan", "girls": 27, "boys": 20 },
    { "country": "Latvia", "girls": 24, "boys": 20 },
    { "country": "France", "girls": 22, "boys": 20 },
    { "country": "Kyrgyzstan", "girls": 25, "boys": 17 },
    { "country": "Czechia", "girls": 23, "boys": 18 },
    { "country": "Ireland", "girls": 19, "boys": 19 },
    { "country": "Slovenia", "girls": 20, "boys": 16 },
    { "country": "Lithuania", "girls": 19, "boys": 15 },
    { "country": "Greece", "girls": 18, "boys": 14 },
    { "country": "Portugal", "girls": 14, "boys": 13 },
    { "country": "Spain", "girls": 11, "boys": 11 },
    { "country": "Denmark", "girls": 8, "boys": 7 },
    { "country": "Iceland", "girls": 7, "boys": 8 },
    { "country": "Norway", "girls": 6, "boys": 5 },
    { "country": "Finland", "girls": 4, "boys": 4 },
    { "country": "Sweden", "girls": 3, "boys": 4 }
  ],
  "summary": {
    "hbsc_average_gender": { "girls": 27, "boys": 23 },
    "hbsc_average_total": 25
  }
}